MANIFEST.in
README.rst
setup.py
crumbs/__init__.py
crumbs/models.py
crumbs/tests.py
crumbs/templates/breadcrumbs/crumbs.html
crumbs/templatetags/__init__.py
crumbs/templatetags/breadcrumb_tags.py
django_crumbs.egg-info/PKG-INFO
django_crumbs.egg-info/SOURCES.txt
django_crumbs.egg-info/dependency_links.txt
django_crumbs.egg-info/not-zip-safe
django_crumbs.egg-info/top_level.txt